mlflow_pytorch_exp/__init__.py
mlflow_pytorch_exp/mlflow_pytorch_exp.py
mlflow_pytorch_exp/templates/train.py
mlflow_pytorch_exp/templates/config/config.py
mlflow_pytorch_exp/templates/dataloader/dataset.py
mlflow_pytorch_exp/templates/losses/loss.py
mlflow_pytorch_exp/templates/metrics/metric.py
mlflow_pytorch_exp/templates/models/model.py
mlflow_pytorch_exp/templates/utils/utils.py
mlflow_pytorch_exp-0.0.1.dist-info/LICENSE
mlflow_pytorch_exp-0.0.1.dist-info/METADATA
mlflow_pytorch_exp-0.0.1.dist-info/WHEEL
mlflow_pytorch_exp-0.0.1.dist-info/entry_points.txt
mlflow_pytorch_exp-0.0.1.dist-info/top_level.txt
mlflow_pytorch_exp-0.0.1.dist-info/RECORD
