Metadata-Version: 2.1
Name: mlflow-pytorch-exp
Version: 0.0.1
Summary: Create a PyTorch project with MLflow boilerplate.
Home-page: https://github.com/kmamine/mlflow_pytorch_exp
Author: M.A.K
Author-email: mohamed.a.kerkouri@gmail.com
License: MIT
License-File: LICENSE
Requires-Dist: mlflow ==2.14.3
Requires-Dist: pynvml ==11.5.3
